[[{"__type__":"cc.Prefab","_name":"BlockChess_1003","data":{"__id__":1},"asyncLoadAssets":null},{"__type__":"cc.Node","_name":"BlockChess","_components":[{"__type__":"cc.Sprite","node":{"__id__":1},"_spriteFrame":{"__uuid__":"7dQ3qCkQtDXr0VlDbbn57i"},"_sizeMode":0},{"__type__":"9bcaftw68pBuZ4RZKNSNS8s","node":{"__id__":1},"uType":4},{"__type__":"4ac68fbU9pNUbyGLy8+zjQS","node":{"__id__":1}}],"_prefab":{"__type__":"cc.PrefabInfo","root":{"__id__":1},"asset":{"__uuid__":"75eyWaxMpCtptp4UsmPWRu"},"fileId":"460xU16EBArZK1fAXRWa2c"},"_contentSize":{"__type__":"cc.Size","width":100,"height":30},"_position":{"__type__":"cc.Vec2","x":249,"y":158}}],{"__type__":"cc.SpriteFrame","content":{"name":"BlockChess_1003","texture":"1e2b19402","rect":[878,1003,64,19],"offset":[-0.5,-1],"originalSize":[65,63]}}]